CHANGELOG.txt
LICENCE.txt
MANIFEST.in
README.txt
setup.py
jwringcentral/__init__.py
jwringcentral/df.py
jwringcentral/exportdata.py
jwringcentral.egg-info/PKG-INFO
jwringcentral.egg-info/SOURCES.txt
jwringcentral.egg-info/dependency_links.txt
jwringcentral.egg-info/top_level.txt
jwringcentral/venv/bin/activate_this.py
jwringcentral/venv/lib/python3.7/site-packages/_virtualenv.py
jwringcentral/venv/lib/python3.7/site-packages/six.py
jwringcentral/venv/lib/python3.7/site-packages/_distutils_hack/__init__.py
jwringcentral/venv/lib/python3.7/site-packages/_distutils_hack/override.py
jwringcentral/venv/lib/python3.7/site-packages/dateutil/__init__.py
jwringcentral/venv/lib/python3.7/site-packages/dateutil/_common.py
jwringcentral/venv/lib/python3.7/site-packages/dateutil/_version.py
jwringcentral/venv/lib/python3.7/site-packages/dateutil/easter.py
jwringcentral/venv/lib/python3.7/site-packages/dateutil/relativedelta.py
jwringcentral/venv/lib/python3.7/site-packages/dateutil/rrule.py
jwringcentral/venv/lib/python3.7/site-packages/dateutil/tzwin.py
jwringcentral/venv/lib/python3.7/site-packages/dateutil/utils.py
jwringcentral/venv/lib/python3.7/site-packages/dateutil/parser/__init__.py
jwringcentral/venv/lib/python3.7/site-packages/dateutil/parser/_parser.py
jwringcentral/venv/lib/python3.7/site-packages/dateutil/parser/isoparser.py
jwringcentral/venv/lib/python3.7/site-packages/dateutil/tz/__init__.py
jwringcentral/venv/lib/python3.7/site-packages/dateutil/tz/_common.py
jwringcentral/venv/lib/python3.7/site-packages/dateutil/tz/_factories.py
jwringcentral/venv/lib/python3.7/site-packages/dateutil/tz/tz.py
jwringcentral/venv/lib/python3.7/site-packages/dateutil/tz/win.py
jwringcentral/venv/lib/python3.7/site-packages/dateutil/zoneinfo/__init__.py
jwringcentral/venv/lib/python3.7/site-packages/dateutil/zoneinfo/rebuild.py
jwringcentral/venv/lib/python3.7/site-packages/numpy/LICENSE.txt
jwringcentral/venv/lib/python3.7/site-packages/numpy/__config__.py
jwringcentral/venv/lib/python3.7/site-packages/numpy/__init__.py
jwringcentral/venv/lib/python3.7/site-packages/numpy/_distributor_init.py
jwringcentral/venv/lib/python3.7/site-packages/numpy-1.20.2.dist-info/LICENSE.txt
jwringcentral/venv/lib/python3.7/site-packages/numpy-1.20.2.dist-info/LICENSES_bundled.txt
jwringcentral/venv/lib/python3.7/site-packages/numpy-1.20.2.dist-info/entry_points.txt
jwringcentral/venv/lib/python3.7/site-packages/numpy-1.20.2.dist-info/top_level.txt
jwringcentral/venv/lib/python3.7/site-packages/pandas-1.2.3.dist-info/entry_points.txt
jwringcentral/venv/lib/python3.7/site-packages/pandas-1.2.3.dist-info/top_level.txt
jwringcentral/venv/lib/python3.7/site-packages/pip-21.0.1.dist-info/LICENSE.txt
jwringcentral/venv/lib/python3.7/site-packages/pip-21.0.1.dist-info/entry_points.txt
jwringcentral/venv/lib/python3.7/site-packages/pip-21.0.1.dist-info/top_level.txt
jwringcentral/venv/lib/python3.7/site-packages/python_dateutil-2.8.1.dist-info/top_level.txt
jwringcentral/venv/lib/python3.7/site-packages/pytz-2021.1.dist-info/LICENSE.txt
jwringcentral/venv/lib/python3.7/site-packages/pytz-2021.1.dist-info/top_level.txt
jwringcentral/venv/lib/python3.7/site-packages/setuptools-54.1.2.dist-info/dependency_links.txt
jwringcentral/venv/lib/python3.7/site-packages/setuptools-54.1.2.dist-info/entry_points.txt
jwringcentral/venv/lib/python3.7/site-packages/setuptools-54.1.2.dist-info/top_level.txt
jwringcentral/venv/lib/python3.7/site-packages/six-1.15.0.dist-info/top_level.txt
jwringcentral/venv/lib/python3.7/site-packages/wheel-0.36.2.dist-info/LICENSE.txt
jwringcentral/venv/lib/python3.7/site-packages/wheel-0.36.2.dist-info/entry_points.txt
jwringcentral/venv/lib/python3.7/site-packages/wheel-0.36.2.dist-info/top_level.txt
