Metadata-Version: 1.1
Name: jwringcentral
Version: 0.0.1
Summary: Some methods on importing/exporting data and DF manipulation
Home-page: UNKNOWN
Author: Jiayi(Mike) Wang
Author-email: jiayiwang08@gmail.com
License: MIT
Platform: UNKNOWN
Classifier: License :: OSI Approved :: MIT License
Classifier: Programming Language :: Python :: 3.9
